{
    "entradas": 5,
    "capas": [
        {
            "neuronas": [
                {
                    "pesos": [
                        -0.5187340464155517,
                        0.7022682241876234,
                        1.9146719302126236,
                        -0.6111013339594004,
                        4.673965558471672,
                        0.4890977611862486
                    ]
                },
                {
                    "pesos": [
                        4.419047669477821,
                        1.7261424703215569,
                        2.3645389253365567,
                        -2.864432725462735,
                        -2.09969196515245,
                        1.5539266784208499
                    ]
                },
                {
                    "pesos": [
                        -3.8641505765460535,
                        -0.5859915925839845,
                        -2.6298840349963903,
                        1.7159603833077814,
                        2.2425174535537424,
                        1.2685930373562315
                    ]
                },
                {
                    "pesos": [
                        3.4905599656449873,
                        4.069799605979682,
                        2.1678564402094365,
                        -0.7060840892334181,
                        0.16332793198786447,
                        -7.29087137490204
                    ]
                },
                {
                    "pesos": [
                        -0.7498531249551857,
                        -0.7748973584698307,
                        -0.20046896471691736,
                        0.38505489052528996,
                        4.821425387579462,
                        -1.863527193334981
                    ]
                },
                {
                    "pesos": [
                        0.3504134571775048,
                        0.300450866634447,
                        -8.631682810372332,
                        2.9653554596194223,
                        -0.949048642358154,
                        1.2912705235819404
                    ]
                },
                {
                    "pesos": [
                        -3.915775154752221,
                        -1.748387339439787,
                        1.2945285287724764,
                        3.9339472593037232,
                        0.5892727002160509,
                        -5.226111686788631
                    ]
                },
                {
                    "pesos": [
                        0.8065519161360425,
                        -2.0180387343722592,
                        -4.592118050840825,
                        1.63116406449711,
                        0.7908147768230779,
                        -6.30783373649682
                    ]
                },
                {
                    "pesos": [
                        0.7737477661689076,
                        0.7709450334280292,
                        -6.4109776049723015,
                        0.5707140834636628,
                        0.2265844818510245,
                        1.494949622032561
                    ]
                },
                {
                    "pesos": [
                        -2.9406427139498947,
                        0.231590904581024,
                        2.949635396438314,
                        6.280865724738664,
                        -2.5071157426534776,
                        -1.8063247857500215
                    ]
                },
                {
                    "pesos": [
                        -3.0474316206951713,
                        -1.1888569282658374,
                        -6.110660144790313,
                        1.0339350091478983,
                        0.14958203718518212,
                        -4.879977138805158
                    ]
                },
                {
                    "pesos": [
                        -2.9405477967285627,
                        3.178757503213606,
                        1.657267684171375,
                        -2.4505888504305946,
                        -5.541714936511847,
                        2.7825074515627546
                    ]
                },
                {
                    "pesos": [
                        8.561921255815133,
                        1.9169741998415057,
                        -2.6169122310049655,
                        0.6053016081204274,
                        7.794079656753095,
                        -0.19752022152122464
                    ]
                },
                {
                    "pesos": [
                        -6.202754919612172,
                        -0.5626238049449694,
                        9.057676567221371,
                        -2.2053600808692524,
                        0.33204320576534424,
                        -2.660968472583478
                    ]
                },
                {
                    "pesos": [
                        -4.982959220830635,
                        -0.776743834507099,
                        -1.2405685197135357,
                        -0.883880630934138,
                        4.889429767976569,
                        3.2569640169913163
                    ]
                },
                {
                    "pesos": [
                        -2.261228450497732,
                        -0.654625832851609,
                        -0.9894351551817854,
                        0.4842302318628715,
                        -5.980477400840487,
                        -0.0439484771343135
                    ]
                }
            ]
        },
        {
            "neuronas": [
                {
                    "pesos": [
                        -2.5588405358998507,
                        4.073121436201555,
                        -2.9230269957046375,
                        2.799913133395175,
                        -4.977515449863591,
                        2.415001164296287,
                        -0.2783116731452685,
                        -4.443250312954568,
                        -3.244442439242248,
                        2.4548415690492456,
                        -2.580642885073689,
                        -1.6726487557113183,
                        -3.02076007774256,
                        0.8479041732841873,
                        -3.346309188462638,
                        5.415023037491717,
                        -0.6614692055500739
                    ]
                },
                {
                    "pesos": [
                        -5.484293230667722,
                        -4.2718624169946,
                        -7.239814395472113,
                        1.779432642729948,
                        0.4956951777024953,
                        0.3231399668001641,
                        1.7823319023293438,
                        3.710431894522507,
                        -0.6077921262717716,
                        -0.4310077513866654,
                        5.642307957377977,
                        5.376463450031652,
                        -2.35495458456563,
                        -2.254730556424192,
                        -6.210508271994493,
                        -4.959098003722789,
                        -2.3093479120563996
                    ]
                },
                {
                    "pesos": [
                        -1.8428736746133372,
                        -3.3476805074458853,
                        0.11985259315973902,
                        -1.1126335750244347,
                        -4.082251433654496,
                        -3.5420648609345142,
                        -4.448254823366733,
                        -2.3800157186371105,
                        -1.4098247658547676,
                        -3.4571995805257467,
                        2.302277588063558,
                        1.4557834823610891,
                        4.366630042211237,
                        -4.436905136063136,
                        3.6062676348282134,
                        -2.0759837831969943,
                        2.6467427304081053
                    ]
                },
                {
                    "pesos": [
                        -4.621859369561847,
                        1.3816455962059517,
                        1.0673472636526427,
                        -5.872699210464677,
                        4.241644235653673,
                        -6.175675185495254,
                        5.689869962146608,
                        -6.113989069473012,
                        -2.6246732727952864,
                        1.4270408703126876,
                        -3.6514791322994244,
                        2.6502232039492557,
                        3.3932059773391097,
                        3.7939562045259185,
                        -4.288435037297985,
                        -7.123775358754289,
                        -4.653164214096787
                    ]
                },
                {
                    "pesos": [
                        -2.7465060543968463,
                        -0.14445206208826475,
                        0.8410265269058328,
                        -5.2589688592692205,
                        1.9567149155257473,
                        -1.6176965237518872,
                        -3.6493558103706705,
                        1.941110951822401,
                        7.793057878741234,
                        -3.3735673255197627,
                        -0.4059531633618648,
                        -7.214686791929538,
                        -5.288824743537254,
                        0.4469453891216076,
                        0.18169145115990554,
                        0.19683489091587283,
                        -3.485011259134959
                    ]
                }
            ]
        }
    ]
}