{
    "entradas": 7,
    "capas": [
        {
            "neuronas": [
                {
                    "pesos": [
                        43.354075941774504,
                        22.13864494009673,
                        1.0172910867113323,
                        64.49262811299866,
                        4.483279598379984,
                        3.560839063089365,
                        3.348694648137555,
                        -0.23560711679174
                    ]
                },
                {
                    "pesos": [
                        -120.27331739217637,
                        29.807022226059292,
                        29.30341640063761,
                        24.101530672432748,
                        14.796443474066743,
                        3.15341858615603,
                        -3.1154388927944625,
                        3.27211801741896
                    ]
                },
                {
                    "pesos": [
                        -113.3046259003042,
                        47.45080307976712,
                        39.59021108308259,
                        18.944292202695124,
                        18.354483216155668,
                        0.15679063019471254,
                        0.84421370730319,
                        1.5047458672588778
                    ]
                },
                {
                    "pesos": [
                        57.77144620774067,
                        58.65993824244969,
                        5.773389470431542,
                        0.2563714055030804,
                        -4.1357496922433254,
                        -1.8396285276903859,
                        -0.34037998208171993,
                        1.6663464446990357
                    ]
                },
                {
                    "pesos": [
                        -82.57267819363562,
                        59.37196460987654,
                        52.4765908310205,
                        13.393416382106134,
                        10.281032568474773,
                        4.3451618799991225,
                        3.1183422155100384,
                        3.274942506065881
                    ]
                },
                {
                    "pesos": [
                        19.577438758692537,
                        48.526086422486685,
                        73.11150921452958,
                        2.083021846936969,
                        6.903821058678416,
                        6.1965730914271555,
                        -1.475457777033124,
                        2.598218417741796
                    ]
                },
                {
                    "pesos": [
                        -124.06759206932368,
                        36.984140820514135,
                        34.8438735156803,
                        7.378101580181267,
                        6.741716828800484,
                        2.7843228977891323,
                        3.0412735528102623,
                        3.5080071583895593
                    ]
                },
                {
                    "pesos": [
                        -45.99152525712365,
                        64.86890823176789,
                        73.3310941111806,
                        16.99103440199851,
                        7.565130586568865,
                        1.160245054567797,
                        -1.0896002595940988,
                        1.9249011759803032
                    ]
                },
                {
                    "pesos": [
                        -12.045830708978416,
                        44.100615236220634,
                        12.034325317509056,
                        70.98404083194325,
                        -3.925126158093329,
                        2.205144352951739,
                        -0.43975636547693264,
                        2.391636772544932
                    ]
                },
                {
                    "pesos": [
                        32.844106684650825,
                        -36.42456664885146,
                        21.49000542639823,
                        6.962877812743891,
                        18.38521839239819,
                        1.52668910334474,
                        1.7766770389932192,
                        1.5313159967652084
                    ]
                },
                {
                    "pesos": [
                        -66.63685801097252,
                        57.26697460249303,
                        18.236808803621184,
                        59.93649615852206,
                        0.04812306230233745,
                        4.501305454765087,
                        1.4221173792636577,
                        -0.0488316014006396
                    ]
                },
                {
                    "pesos": [
                        -124.44768515899398,
                        42.43716400519593,
                        50.917758356386045,
                        13.529144918641094,
                        6.0138279352118795,
                        7.822182322435859,
                        2.129932820180682,
                        2.315654128505117
                    ]
                },
                {
                    "pesos": [
                        -126.79656359520916,
                        39.18588345079369,
                        29.019878201522722,
                        29.24339998433957,
                        23.33073902589936,
                        4.532857436034452,
                        4.225997492282903,
                        0.008753131146442253
                    ]
                },
                {
                    "pesos": [
                        -122.36003637130169,
                        30.31593560983816,
                        33.94436880596161,
                        15.967951773583362,
                        13.713728069689083,
                        7.2483993998655665,
                        1.5506388076055482,
                        -3.5870613236389577
                    ]
                },
                {
                    "pesos": [
                        -99.68967979999672,
                        48.5238229975761,
                        39.49750383583633,
                        25.402676721675526,
                        11.918135970514141,
                        0.9493627978396006,
                        3.834637427848817,
                        0.3329709128384425
                    ]
                },
                {
                    "pesos": [
                        37.85730620432636,
                        70.55338052467903,
                        10.250655699084838,
                        0.21055213285837276,
                        -9.99907160362608,
                        -0.015179505665951824,
                        2.0388089149213036,
                        1.950499943208838
                    ]
                },
                {
                    "pesos": [
                        -97.52013620817411,
                        50.8955975851417,
                        57.507409177291784,
                        15.85935366570014,
                        -0.26790549472079606,
                        0.902591282538507,
                        1.7140622431442967,
                        2.8213640865104925
                    ]
                },
                {
                    "pesos": [
                        -86.11744058123153,
                        44.918917571259264,
                        22.282840524044033,
                        20.571026339752827,
                        38.56313832719648,
                        4.051269535971943,
                        -0.5197410223021798,
                        -3.3772116498862728
                    ]
                },
                {
                    "pesos": [
                        -103.82450162485911,
                        28.63804526698671,
                        28.13512344748716,
                        14.034819216319681,
                        12.003482157947412,
                        -0.515695187273264,
                        3.98319094052592,
                        1.2635384815618829
                    ]
                },
                {
                    "pesos": [
                        77.86525641066483,
                        57.96552023207537,
                        1.6169816496380882,
                        -2.2299970645401506,
                        -4.498620456622771,
                        -2.132622967010744,
                        0.7693858466841833,
                        -1.3193808200387254
                    ]
                },
                {
                    "pesos": [
                        76.4558469050995,
                        40.087252048691305,
                        -33.38707936299773,
                        -13.471689902737742,
                        -7.02414803521048,
                        -0.7597067345787445,
                        2.708168053485928,
                        -0.2621693983626133
                    ]
                },
                {
                    "pesos": [
                        -6.604941362545282,
                        70.42783884758342,
                        71.90764036609923,
                        15.465096408523195,
                        15.819415220921394,
                        0.40235532950016667,
                        2.8508355560888323,
                        -0.9371304963901861
                    ]
                },
                {
                    "pesos": [
                        -126.09007582710181,
                        23.85830496748623,
                        27.753516469730606,
                        26.46657625225466,
                        13.522050244093295,
                        -2.963750325494782,
                        -3.622361997259234,
                        14.721206585484559
                    ]
                },
                {
                    "pesos": [
                        -21.421047025488736,
                        52.75594083327413,
                        12.471326651741602,
                        8.646314164832136,
                        55.984135147982656,
                        4.660050858335993,
                        0.9676207807947738,
                        -1.0301014033211016
                    ]
                },
                {
                    "pesos": [
                        -40.515832504030755,
                        7.5959396495767075,
                        -0.33618044367645067,
                        0.46408731505185635,
                        -2.4076294520494343,
                        -2.6993581395807955,
                        2.944215460136968,
                        -3.2524361522610734
                    ]
                },
                {
                    "pesos": [
                        -4.964395251245289,
                        77.96854706711159,
                        6.385775124366125,
                        -0.7273237151246494,
                        -3.2649346525034093,
                        1.9372272010963134,
                        3.3292026077346275,
                        1.3163984464857834
                    ]
                },
                {
                    "pesos": [
                        -64.98129665821438,
                        60.82555233959918,
                        58.535144266281165,
                        20.164678970309975,
                        8.717231529930915,
                        4.372057456453844,
                        0.3814476635977148,
                        2.727773303223464
                    ]
                },
                {
                    "pesos": [
                        8.647235293393932,
                        72.88413271846042,
                        12.782000955765625,
                        19.669370065025745,
                        10.25263705857113,
                        2.7791230386822594,
                        1.750775771905677,
                        2.752438365028954
                    ]
                },
                {
                    "pesos": [
                        38.78174968642821,
                        51.25258951893222,
                        -15.844310374068233,
                        -9.070687368925094,
                        51.07061790529499,
                        1.1586610456875537,
                        0.9282158961062993,
                        -2.1326113620715867
                    ]
                },
                {
                    "pesos": [
                        47.09549433890683,
                        35.30772288467722,
                        58.7737310002573,
                        4.7996228161776315,
                        -0.6292761073923168,
                        4.745100757568529,
                        -0.9245582413511406,
                        -0.28129641059261495
                    ]
                },
                {
                    "pesos": [
                        69.49091108216912,
                        -42.74012348392575,
                        51.42609940139438,
                        -5.5732800774678735,
                        -5.853737404695491,
                        1.604363491362919,
                        1.549608755875257,
                        2.451700209587584
                    ]
                },
                {
                    "pesos": [
                        -60.806387712349256,
                        53.646668293497186,
                        26.22475477729969,
                        6.475680768765234,
                        41.20770601757702,
                        4.565938918452924,
                        3.972125669441315,
                        1.392369842504752
                    ]
                }
            ]
        },
        {
            "neuronas": [
                {
                    "pesos": [
                        -400.70576282403573,
                        107.25332914986085,
                        151.51834475606168,
                        158.55644601021797,
                        133.51252945818462,
                        135.51621226975882,
                        117.50891766187402,
                        153.83389803596208,
                        126.72561260879462,
                        85.32222799056375,
                        129.8759995794461,
                        102.67953882199922,
                        158.54647918269225,
                        175.92671720521446,
                        163.88162369105365,
                        124.41668388395097,
                        120.59827318298312,
                        146.6246400604621,
                        108.49463554441253,
                        136.68935021309892,
                        139.56037823900954,
                        139.99038647144445,
                        122.02745438535143,
                        168.3429520118831,
                        92.99384057809847,
                        94.17193744383252,
                        112.9105751636042,
                        134.69224129414445,
                        94.75657626377345,
                        92.88485209172326,
                        117.90722209058069,
                        149.1396694260861,
                        100.28444343184275
                    ]
                }
            ]
        }
    ]
}